[
  {
    "id": 1,
    "title": "kumbalangi Nights",
    "ytid": "bNyKd0PUx04"
  },
  {
    "id": 2,
    "title": "Premam",
    "ytid": "yjaFvFuQ-QM"
  },
  {
    "id": 3,
    "title": "Godha",
    "ytid": "aBMFzWS1X3E"
  },
  {
    "id": 4,
    "title": "Jacobinte Swargarajyam",
    "ytid": "Jo9oF9EZT44"
  },
  {
    "id": 5,
    "title": "Angamaly Diaries",
    "ytid": "9mRG1GVxtkY"
  },
  {
    "id": 6,
    "title": "Ee.Ma.Yau",
    "ytid": "mZNDgzLsPZ8"
  },
  {
    "id": 7,
    "title": "Vettam",
    "ytid": "40nfhLC7i84"
  },
  {
    "id": 8,
    "title": "Kunjiramayanam",
    "ytid": "axDSnoZ2zIM"
  },
  {
    "id": 9,
    "title": "Anandabhadram",
    "ytid": "lkS5CBNsB4g"
  },
  {
    "id": 10,
    "title": "Ayal Katha Ezhuthukayanu",
    "ytid": "wD9Fh468UOU"
  },
  {
    "id": 11,
    "title": "Chandrolsavam",
    "ytid": "1GUDP6EU1f0"
  },
  {
    "id": 12,
    "title": "Hey Jude",
    "ytid": "99LEGcE-_yA"
  },
  {
    "id": 13,
    "title": "Joseph",
    "ytid": "Zhrau8ZfEr0"
  },
  {
    "id": 14,
    "title": "The Great Indian Kitchen",
    "ytid": "sYyfxVAPdTo"
  },
  {
    "id": 15,
    "title": "Bodyguard",
    "ytid": "TPnhi6JTG1c"
  },
  {
    "id": 16,
    "title": "Oru Vadakkan Selfie",
    "ytid": "Wea0yLSdyGM"
  },
  {
    "id": 17,
    "title": "Narasimham",
    "ytid": "Z3g5qGQK7eI"
  },
  {
    "id": 18,
    "title": "Kakkakuyil",
    "ytid": "jW2tFrp_4QQ"
  },
  {
    "id": 19,
    "title": "Pullipulikalum Aattinkuttiyum",
    "ytid": "k-MNkfmyEHg"
  },
  {
    "id": 20,
    "title": "Manichithrathazhu",
    "ytid": "MLmT2Bbu1d0"
  },
  {
    "id": 21,
    "title": "Vellimoonga",
    "ytid": "f6y-28rQYls"
  },
  {
    "id": 22,
    "title": "Devadoothan",
    "ytid": "mmLLUOqu4p0"
  },
  {
    "id": 23,
    "title": "Azhakiya Ravanan",
    "ytid": "uYiEzQU-jRg"
  },
  {
    "id": 24,
    "title": "Meesha Madhavan",
    "ytid": "6U89t0c5TBQ"
  },
  {
    "id": 25,
    "title": "Manichithrathazhu - Empire version",
    "ytid": "tQDTJdL1Fpc"
  },
  {
    "id": 26,
    "title": "Punjabi House",
    "ytid": "uH207PW77Wo"
  },
  {
    "id": 27,
    "title": "Sandhesham",
    "ytid": "PJ8eni68puM"
  },
  {
    "id": 28,
    "title": "Vaishali",
    "ytid": "wJpnY0oNepE"
  },
  {
    "id": 29,
    "title": "Aniyathipravu",
    "ytid": "JR34yKXJggM"
  },
  {
    "id": 30,
    "title": "Ayal Katha Ezhuthukayanu (Empire)",
    "ytid": "Jw8BQdEl-AA"
  },
  {
    "id": 31,
    "title": "Ramji Rao Speaking",
    "ytid": "uZ-zpSIYJnw"
  },
  {
    "id": 32,
    "title": "Niram",
    "ytid": "QAWR-GVaiQo"
  },
  {
    "id": 33,
    "title": "Chandralekha",
    "ytid": "_oi8SClG2bY"
  },
  {
    "id": 34,
    "title": "Akashadoothu",
    "ytid": "c1rIRkbofIw"
  },
  {
    "id": 35,
    "title": "Yodha",
    "ytid": "p1eo1o1j0pM"
  },
  {
    "id": 36,
    "title": "Thaniyavarthanam",
    "ytid": "ultBsK_Qmwg"
  },
  {
    "id": 37,
    "title": "Vietnam Colony",
    "ytid": "WZpq5vs0dBQ"
  },
  {
    "id": 38,
    "title": "Mannar Mathai Speaking",
    "ytid": "xeVgrYrcyTw"
  },
  {
    "id": 39,
    "title": "Thenkasipattanam",
    "ytid": "tsIwzxRP8T0"
  },
  {
    "id": 40,
    "title": "Hallo",
    "ytid": "T9C4v6lEBVA"
  },
  {
    "id": 41,
    "title": "Indraprastham",
    "ytid": "VM1rLiBDR6g"
  },
  {
    "id": 42,
    "title": "One Man Show",
    "ytid": "d2x6hxiMxVc"
  },
  {
    "id": 43,
    "title": "Spadikam",
    "ytid": "349z-tk5RUM"
  },
  {
    "id": 44,
    "title": "Pattabhishekam",
    "ytid": "a_KDfnIRdiU"
  },
  {
    "id": 45,
    "title": "Hitler",
    "ytid": "i3owqx5TOTw"
  },
  {
    "id": 46,
    "title": "Friends",
    "ytid": "OlakJF7FbNU"
  },
  {
    "id": 47,
    "title": "New Delhi",
    "ytid": "uB_S8Uf0n4U"
  },
  {
    "id": 48,
    "title": "Rudraksham",
    "ytid": "1cgsPRz08sU"
  },
  {
    "id": 49,
    "title": "Dasharatham",
    "ytid": "eYfXbIHeNiY"
  },
  {
    "id": 50,
    "title": "Ponmuttayidunna Tharavu",
    "ytid": "7G3tgdSJi6k"
  }
]